pysimpledraw/__init__.py
pysimpledraw/__main__.py
pysimpledraw/main.py
pysimpledraw-0.1.1.dist-info/METADATA
pysimpledraw-0.1.1.dist-info/WHEEL
pysimpledraw-0.1.1.dist-info/entry_points.txt
pysimpledraw-0.1.1.dist-info/top_level.txt
pysimpledraw-0.1.1.dist-info/RECORD
