Metadata-Version: 2.4
Name: pysimpledraw
Version: 0.1.1
Summary: simple yet all you need for protyping
Project-URL: Homepage, https://github.com/fxyzbtc/pysimpledraw
Requires-Python: >=3.12
Requires-Dist: freesimplegui>=5.2.0.post1
Requires-Dist: pillow>=11.2.1
Requires-Dist: pydantic>=2.11.4
Requires-Dist: pyperclip>=1.9.0
Requires-Dist: pysimplegui>=5.0.8.3
Requires-Dist: python-pyper>=0.4.4
